statgis/__init__.py
statgis/gee/__init__.py
statgis/gee/classification.py
statgis/gee/landsat_functions.py
statgis/gee/river_analysis.py
statgis/gee/sample.py
statgis/gee/sentinel_functions.py
statgis/gee/shoreline_analysis.py
statgis/gee/terrain_analysis.py
statgis/gee/time_series_analysis.py
statgis/gee/utils.py
statgis/gee/zonal_statistics.py
statgis/statgis.py
statgis/statutils/__init__.py
statgis/statutils/plots.py
statgis/statutils/stats.py
statgis-1.1.2.dist-info/LICENSE
statgis-1.1.2.dist-info/METADATA
statgis-1.1.2.dist-info/WHEEL
statgis-1.1.2.dist-info/RECORD
