Metadata-Version: 2.1
Name: statgis
Version: 1.1.2
Summary: Tools for improve work with geospatial data in Python
License: MIT
Author: Sebástian Narváez-Salcedo
Author-email: sanarvaezstatgis@gmail.com
Requires-Python: >=3.8,<3.12
Classifier: License :: OSI Approved :: MIT License
Classifier: Programming Language :: Python :: 3
Classifier: Programming Language :: Python :: 3.8
Classifier: Programming Language :: Python :: 3.9
Classifier: Programming Language :: Python :: 3.10
Classifier: Programming Language :: Python :: 3.11
Requires-Dist: earthengine-api (>=0.1.335)
Requires-Dist: matplotlib (>=3.2.2)
Requires-Dist: pandas (>=1.3.5)
Requires-Dist: scipy (>=1.7.3)
